undebt/__init__.py
undebt/__main__.py
undebt/cmd/__init__.py
undebt/cmd/logger.py
undebt/cmd/logic.py
undebt/cmd/main.py
undebt/examples/__init__.py
undebt/examples/attribute_to_function.py
undebt/examples/class_inherit_object.py
undebt/examples/contextlib_nested.py
undebt/examples/dbl_quote_docstring.py
undebt/examples/exec_function.py
undebt/examples/hex_to_bitshift.py
undebt/examples/method_to_function.py
undebt/examples/nl_at_eof.py
undebt/examples/remove_needless_u_specifier.py
undebt/examples/remove_unused_import.py
undebt/examples/sqla_count.py
undebt/pattern/__init__.py
undebt/pattern/common.py
undebt/pattern/interface.py
undebt/pattern/python.py
undebt/pattern/testing.py
undebt/pattern/util.py
undebt-0.2.3.dist-info/DESCRIPTION.rst
undebt-0.2.3.dist-info/METADATA
undebt-0.2.3.dist-info/RECORD
undebt-0.2.3.dist-info/WHEEL
undebt-0.2.3.dist-info/entry_points.txt
undebt-0.2.3.dist-info/metadata.json
undebt-0.2.3.dist-info/top_level.txt
