Metadata-Version: 2.0
Name: undebt
Version: 0.2.3
Summary: A fast, straightforward, reliable tool for performing massive, automated code refactoring
Home-page: https://github.com/Yelp/undebt
Author: UNKNOWN
Author-email: UNKNOWN
License: Copyright Yelp, Inc. 2016
Platform: UNKNOWN
Classifier: Programming Language :: Python :: 2
Classifier: Programming Language :: Python :: 3
Classifier: License :: OSI Approved :: Apache Software License
Classifier: Intended Audience :: Developers
Classifier: Topic :: Software Development
Classifier: Topic :: Utilities
Classifier: Environment :: Console
Classifier: Operating System :: OS Independent
Classifier: Development Status :: 5 - Production/Stable
Requires-Dist: pyparsing
Provides-Extra: testing
Requires-Dist: coverage; extra == 'testing'
Requires-Dist: flake8; extra == 'testing'
Requires-Dist: mock; extra == 'testing'
Requires-Dist: pytest; extra == 'testing'
